gprMax/__init__.py
gprMax/__main__.py
gprMax/_version.py
gprMax/constants.py
gprMax/exceptions.py
gprMax/fields_outputs.py
gprMax/fields_updates_ext.c
gprMax/fields_updates_ext.cpython-37m-x86_64-linux-gnu.so
gprMax/fields_updates_gpu.py
gprMax/fractals.py
gprMax/fractals_generate_ext.c
gprMax/fractals_generate_ext.cpython-37m-x86_64-linux-gnu.so
gprMax/geometry_outputs.py
gprMax/geometry_outputs_ext.c
gprMax/geometry_outputs_ext.cpython-37m-x86_64-linux-gnu.so
gprMax/geometry_primitives_ext.c
gprMax/geometry_primitives_ext.cpython-37m-x86_64-linux-gnu.so
gprMax/gprMax.py
gprMax/grid.py
gprMax/input_cmd_funcs.py
gprMax/input_cmds_file.py
gprMax/input_cmds_geometry.py
gprMax/input_cmds_multiuse.py
gprMax/input_cmds_singleuse.py
gprMax/materials.py
gprMax/model_build_run.py
gprMax/optimisation_taguchi.py
gprMax/pml.py
gprMax/pml_updates_ext.c
gprMax/pml_updates_ext.cpython-37m-x86_64-linux-gnu.so
gprMax/pml_updates_gpu.py
gprMax/receivers.py
gprMax/snapshots.py
gprMax/snapshots_ext.c
gprMax/snapshots_ext.cpython-37m-x86_64-linux-gnu.so
gprMax/snapshots_gpu.py
gprMax/source_updates_gpu.py
gprMax/sources.py
gprMax/utilities.py
gprMax/waveforms.py
gprMax/yee_cell_build_ext.c
gprMax/yee_cell_build_ext.cpython-37m-x86_64-linux-gnu.so
gprMax/yee_cell_setget_rigid_ext.c
gprMax/yee_cell_setget_rigid_ext.cpython-37m-x86_64-linux-gnu.so
tests/__init__.py
tests/analytical_solutions.py
tests/test_experimental.py
tests/test_input_cmd_funcs.py
tests/test_models.py
tests/benchmarking/__init__.py
tests/benchmarking/bench_100x100x100.in
tests/benchmarking/bench_150x150x150.in
tests/benchmarking/bench_200x200x200.in
tests/benchmarking/bench_300x300x300.in
tests/benchmarking/bench_400x400x400.in
tests/benchmarking/bench_450x450x450.in
tests/benchmarking/plot_benchmark.py
tests/benchmarking/results/Linux/Dell_PowerEdge_R630/Dell_PowerEdge_R630.png
tests/benchmarking/results/Linux/Dell_PowerEdge_R630/bench_100x100x100.npz
gprMax-3.1.4.dist-info/LICENSE
gprMax-3.1.4.dist-info/METADATA
gprMax-3.1.4.dist-info/WHEEL
gprMax-3.1.4.dist-info/top_level.txt
gprMax-3.1.4.dist-info/RECORD
