Metadata-Version: 2.1
Name: gprMax
Version: 3.1.4
Summary: Electromagnetic Modelling Software based on the Finite-Difference Time-Domain (FDTD) method
Home-page: http://www.gprmax.com
Author: Craig Warren and Antonis Giannopoulos
License: GPLv3+
Platform: UNKNOWN
Classifier: Environment :: Console
Classifier: License :: OSI Approved :: GNU General Public License v3 or later (GPLv3+)
Classifier: Operating System :: MacOS
Classifier: Operating System :: Microsoft :: Windows
Classifier: Operating System :: POSIX :: Linux
Classifier: Programming Language :: Cython
Classifier: Programming Language :: Python :: 3
Classifier: Topic :: Scientific/Engineering
Requires-Python: >3.6
Requires-Dist: colorama
Requires-Dist: cython
Requires-Dist: h5py
Requires-Dist: jupyter
Requires-Dist: matplotlib
Requires-Dist: numpy
Requires-Dist: psutil
Requires-Dist: scipy
Requires-Dist: terminaltables
Requires-Dist: tqdm
